LICENSE
MANIFEST.in
README.rst
setup.cfg
setup.py
src/os_urlpattern/VERSION
src/os_urlpattern/__init__.py
src/os_urlpattern/cmdline.py
src/os_urlpattern/compat.py
src/os_urlpattern/definition.py
src/os_urlpattern/exceptions.py
src/os_urlpattern/formatter.py
src/os_urlpattern/parse_utils.py
src/os_urlpattern/parsed_piece_view.py
src/os_urlpattern/parser.py
src/os_urlpattern/pattern.py
src/os_urlpattern/pattern_cluster.py
src/os_urlpattern/pattern_maker.py
src/os_urlpattern/pattern_matcher.py
src/os_urlpattern/piece_pattern_node.py
src/os_urlpattern/utils.py
src/os_urlpattern.egg-info/PKG-INFO
src/os_urlpattern.egg-info/SOURCES.txt
src/os_urlpattern.egg-info/dependency_links.txt
src/os_urlpattern.egg-info/entry_points.txt
src/os_urlpattern.egg-info/not-zip-safe
src/os_urlpattern.egg-info/requires.txt
src/os_urlpattern.egg-info/top_level.txt
src/os_urlpattern/config/__init__.py
src/os_urlpattern/config/default_config.cfg
tests/__init__.py
tests/test_cmdline.py
tests/test_config.py
tests/test_formatter.py
tests/test_parse_utils.py
tests/test_parsed_piece_view.py
tests/test_pattern.py
tests/test_pattern_maker.py
tests/test_pattern_matcher.py
tests/test_piece_pattern_node.py
tests/data/urls_example.txt