Metadata-Version: 2.1
Name: os-urlpattern
Version: 0.1.11
Summary: Cluster url pattern automatically.
Home-page: https://github.com/cfhamlet/os-urlpattern
Author: Ozzy
Author-email: cfhamlet@gmail.com
License: MIT License
Platform: UNKNOWN
Classifier: Development Status :: 2 - Pre-Alpha
Classifier: Intended Audience :: Developers
Classifier: License :: OSI Approved :: MIT License
Classifier: Natural Language :: English
Classifier: Programming Language :: Python :: 2
Classifier: Programming Language :: Python :: 2.7
Classifier: Programming Language :: Python :: 3
Classifier: Programming Language :: Python :: 3.6
Classifier: Programming Language :: Python :: Implementation :: CPython
Classifier: Programming Language :: Python :: Implementation :: PyPy
Provides-Extra: ete-tree
Provides-Extra: memory
